ipsetgen
