Metadata-Version: 1.1
Name: ipsetgen
Version: v0.0.2
Summary: role-based ipset generator
Home-page: https://github.com/fly/ipsetgen
Author: Jon Chen
Author-email: bsd@voltaire.sh
License: BSD 3-Clause License
Platform: UNKNOWN
Classifier: Intended Audience :: Developers
Classifier: License :: OSI Approved :: BSD License
Classifier: Operating System :: OS Independent
Classifier: Programming Language :: Python
Classifier: Programming Language :: Python :: 3
Classifier: Programming Language :: Python :: 3.2
Classifier: Programming Language :: Python :: 3.3
